odoo/addons/mail_forward/README.rst
odoo/addons/mail_forward/__init__.py
odoo/addons/mail_forward/__manifest__.py
odoo/addons/mail_forward/i18n/ca.po
odoo/addons/mail_forward/i18n/es.po
odoo/addons/mail_forward/i18n/it.po
odoo/addons/mail_forward/i18n/mail_forward.pot
odoo/addons/mail_forward/models/__init__.py
odoo/addons/mail_forward/models/ir_model.py
odoo/addons/mail_forward/models/mail_message.py
odoo/addons/mail_forward/models/mail_thread.py
odoo/addons/mail_forward/readme/CONFIGURE.md
odoo/addons/mail_forward/readme/CONTRIBUTORS.md
odoo/addons/mail_forward/readme/DESCRIPTION.md
odoo/addons/mail_forward/readme/USAGE.md
odoo/addons/mail_forward/static/description/icon.png
odoo/addons/mail_forward/static/description/index.html
odoo/addons/mail_forward/static/src/components/forward_message/forward_message.esm.js
odoo/addons/mail_forward/static/src/components/forward_message/forward_message.xml
odoo/addons/mail_forward/static/src/core/common/message_actions.esm.js
odoo/addons/mail_forward/static/tests/tours/mail_forward.esm.js
odoo/addons/mail_forward/tests/__init__.py
odoo/addons/mail_forward/tests/test_mail_forward.py
odoo/addons/mail_forward/views/ir_model_views.xml
odoo/addons/mail_forward/wizards/__init__.py
odoo/addons/mail_forward/wizards/mail_compose_message.py
odoo/addons/mail_forward/wizards/mail_compose_message_view.xml
odoo_addon_mail_forward-17.0.2.0.1.4.dist-info/METADATA
odoo_addon_mail_forward-17.0.2.0.1.4.dist-info/WHEEL
odoo_addon_mail_forward-17.0.2.0.1.4.dist-info/top_level.txt
odoo_addon_mail_forward-17.0.2.0.1.4.dist-info/RECORD
